{
  "featured": [
    {
      "title": "Selected Mixes",
      "platform": "soundcloud",
      "embed_url": "https://w.soundcloud.com/player/?url=https%3A//soundcloud.com/prod-suyan&color=%23ffffff&auto_play=false&hide_related=true&show_comments=false&show_user=true&show_reposts=false&show_teaser=false&visual=true",
      "external_url": "https://soundcloud.com/prod-suyan",
      "date": "2026"
    },
    {
      "title": "Recent Releases",
      "platform": "spotify",
      "embed_url": "https://open.spotify.com/embed/artist/3KiOdFDnsNyoomZyh0hOfs?utm_source=generator&theme=0",
      "external_url": "https://open.spotify.com/artist/3KiOdFDnsNyoomZyh0hOfs",
      "date": "2026"
    }
  ],
  "archive": []
}
